Metadata-Version: 2.1
Name: pulumi-powerdns
Version: 0.0.4
Summary: The Pulumi PowerDNS provider provides resources to interact with a PowerDNS Authoritative DNS Server.
Home-page: https://pulumi.com
License: MPL-2.0
Project-URL: Repository, https://github.com/nextpart/pulumi-powerdns-native
Keywords: category/infrastructure kind/native pulumi powerdns dns
Platform: UNKNOWN
Requires-Python: >=3.7
